{
  "data": {
    "uri": "https://fedlex.data.admin.ch/eli/cc/2009/29/20090331",
    "type": [
      "Consolidation",
      "Work"
    ],
    "attributes": {
      "created": {
        "xsd:dateTime": [
          "2009-03-30T22:00:00.000Z"
        ]
      },
      "dateEndApplicability": {
        "xsd:date": "2012-12-31"
      },
      "modified": {
        "xsd:dateTime": [
          "2009-03-30T22:00:00.000Z"
        ]
      },
      "isMemberOf": {
        "rdfs:Resource": "https://fedlex.data.admin.ch/eli/cc/2009/29"
      },
      "dateApplicability": {
        "xsd:date": "2009-03-31"
      }
    },
    "references": {
      "isRealizedBy": [
        "https://fedlex.data.admin.ch/eli/cc/2009/29/20090331/de",
        "https://fedlex.data.admin.ch/eli/cc/2009/29/20090331/it",
        "https://fedlex.data.admin.ch/eli/cc/2009/29/20090331/rm",
        "https://fedlex.data.admin.ch/eli/cc/2009/29/20090331/en",
        "https://fedlex.data.admin.ch/eli/cc/2009/29/20090331/fr"
      ]
    }
  },
  "included": [
    {
      "uri": "https://fedlex.data.admin.ch/eli/cc/2009/29/20090331/de",
      "type": "Expression",
      "references": {
        "isEmbodiedBy": [
          "https://fedlex.data.admin.ch/eli/cc/2009/29/20090331/de/pdf-a"
        ],
        "language": "http://publications.europa.eu/resource/authority/language/DEU"
      },
      "attributes": {
        "title": {
          "xsd:string": "Consolidation: 941.261 - 2009-03-31"
        }
      }
    },
    {
      "uri": "https://fedlex.data.admin.ch/eli/cc/2009/29/20090331/it",
      "type": "Expression",
      "references": {
        "isEmbodiedBy": [
          "https://fedlex.data.admin.ch/eli/cc/2009/29/20090331/it/pdf-a"
        ],
        "language": "http://publications.europa.eu/resource/authority/language/ITA"
      },
      "attributes": {
        "title": {
          "xsd:string": "Consolidation: 941.261 - 2009-03-31"
        }
      }
    },
    {
      "uri": "https://fedlex.data.admin.ch/eli/cc/2009/29/20090331/rm",
      "type": "Expression",
      "references": {
        "language": "http://publications.europa.eu/resource/authority/language/ROH"
      },
      "attributes": {
        "title": {
          "xsd:string": "Consolidation: 941.261 - 2009-03-31"
        }
      }
    },
    {
      "uri": "https://fedlex.data.admin.ch/eli/cc/2009/29/20090331/en",
      "type": "Expression",
      "references": {
        "language": "http://publications.europa.eu/resource/authority/language/ENG"
      },
      "attributes": {
        "title": {
          "xsd:string": "Consolidation: 941.261 - 2009-03-31"
        }
      }
    },
    {
      "uri": "https://fedlex.data.admin.ch/eli/cc/2009/29/20090331/fr",
      "type": "Expression",
      "references": {
        "isEmbodiedBy": [
          "https://fedlex.data.admin.ch/eli/cc/2009/29/20090331/fr/pdf-a"
        ],
        "language": "http://publications.europa.eu/resource/authority/language/FRA"
      },
      "attributes": {
        "title": {
          "xsd:string": "Consolidation: 941.261 - 2009-03-31"
        }
      }
    },
    {
      "uri": "https://fedlex.data.admin.ch/eli/cc/2009/29/20090331/de/pdf-a",
      "type": "Manifestation",
      "references": {
        "rightsHolder": "https://fedlex.data.admin.ch/vocabulary/legal-institution/2",
        "publisher": "https://fedlex.data.admin.ch/vocabulary/legal-institution/2"
      },
      "attributes": {
        "isExemplifiedByPrivate": {
          "rdfs:Resource": "https://intranet.fedlex.admin.ch/casematesbo/filestore/fedlex.data.admin.ch/eli/cc/2009/29/20090331/de/pdf-a/fedlex-data-admin-ch-eli-cc-2009-29-20090331-de-pdf-a.pdf"
        },
        "userFormat": {
          "rdfs:Resource": "https://fedlex.data.admin.ch/vocabulary/user-format/pdf-a"
        },
        "numberOfPages": {
          "xsd:int": [
            4
          ]
        },
        "format": {
          "rdfs:Resource": "http://publications.europa.eu/resource/authority/file-type/PDF"
        },
        "isExemplifiedBy": {
          "rdfs:Resource": "https://fedlex.data.admin.ch/filestore/fedlex.data.admin.ch/eli/cc/2009/29/20090331/de/pdf-a/fedlex-data-admin-ch-eli-cc-2009-29-20090331-de-pdf-a.pdf"
        }
      }
    },
    {
      "uri": "http://publications.europa.eu/resource/authority/language/DEU",
      "type": [
        "Concept",
        "Language"
      ]
    },
    {
      "uri": "https://fedlex.data.admin.ch/eli/cc/2009/29/20090331/it/pdf-a",
      "type": "Manifestation",
      "references": {
        "rightsHolder": "https://fedlex.data.admin.ch/vocabulary/legal-institution/2",
        "publisher": "https://fedlex.data.admin.ch/vocabulary/legal-institution/2"
      },
      "attributes": {
        "isExemplifiedByPrivate": {
          "rdfs:Resource": "https://intranet.fedlex.admin.ch/casematesbo/filestore/fedlex.data.admin.ch/eli/cc/2009/29/20090331/it/pdf-a/fedlex-data-admin-ch-eli-cc-2009-29-20090331-it-pdf-a.pdf"
        },
        "userFormat": {
          "rdfs:Resource": "https://fedlex.data.admin.ch/vocabulary/user-format/pdf-a"
        },
        "numberOfPages": {
          "xsd:int": [
            4
          ]
        },
        "format": {
          "rdfs:Resource": "http://publications.europa.eu/resource/authority/file-type/PDF"
        },
        "isExemplifiedBy": {
          "rdfs:Resource": "https://fedlex.data.admin.ch/filestore/fedlex.data.admin.ch/eli/cc/2009/29/20090331/it/pdf-a/fedlex-data-admin-ch-eli-cc-2009-29-20090331-it-pdf-a.pdf"
        }
      }
    },
    {
      "uri": "http://publications.europa.eu/resource/authority/language/ITA",
      "type": [
        "Concept",
        "Language"
      ]
    },
    {
      "uri": "http://publications.europa.eu/resource/authority/language/ROH",
      "type": [
        "Concept",
        "Language"
      ]
    },
    {
      "uri": "http://publications.europa.eu/resource/authority/language/ENG",
      "type": [
        "Concept",
        "Language"
      ]
    },
    {
      "uri": "https://fedlex.data.admin.ch/eli/cc/2009/29/20090331/fr/pdf-a",
      "type": "Manifestation",
      "references": {
        "rightsHolder": "https://fedlex.data.admin.ch/vocabulary/legal-institution/2",
        "publisher": "https://fedlex.data.admin.ch/vocabulary/legal-institution/2"
      },
      "attributes": {
        "isExemplifiedByPrivate": {
          "rdfs:Resource": "https://intranet.fedlex.admin.ch/casematesbo/filestore/fedlex.data.admin.ch/eli/cc/2009/29/20090331/fr/pdf-a/fedlex-data-admin-ch-eli-cc-2009-29-20090331-fr-pdf-a.pdf"
        },
        "userFormat": {
          "rdfs:Resource": "https://fedlex.data.admin.ch/vocabulary/user-format/pdf-a"
        },
        "numberOfPages": {
          "xsd:int": [
            6
          ]
        },
        "format": {
          "rdfs:Resource": "http://publications.europa.eu/resource/authority/file-type/PDF"
        },
        "isExemplifiedBy": {
          "rdfs:Resource": "https://fedlex.data.admin.ch/filestore/fedlex.data.admin.ch/eli/cc/2009/29/20090331/fr/pdf-a/fedlex-data-admin-ch-eli-cc-2009-29-20090331-fr-pdf-a.pdf"
        }
      }
    },
    {
      "uri": "http://publications.europa.eu/resource/authority/language/FRA",
      "type": [
        "Concept",
        "Language"
      ]
    },
    {
      "uri": "https://fedlex.data.admin.ch/vocabulary/legal-institution/2",
      "type": [
        "Concept",
        "LegalInstitution"
      ]
    }
  ],
  "graph": "https://fedlex.data.admin.ch/eli/cc/2009/29/20090331/graph",
  "facets": {
    "consolidates": [
      {
        "dateDocument": "2008-11-28",
        "expression": {
          "http://publications.europa.eu/resource/authority/language/DEU": {
            "manifestation": [
              {
                "format": "http://publications.europa.eu/resource/authority/file-type/DOC",
                "fileUrl": "https://fedlex.data.admin.ch/filestore/fedlex.data.admin.ch/eli/oc/2009/29/de/doc/fedlex-data-admin-ch-eli-oc-2009-29-de-doc.doc",
                "uri": "https://fedlex.data.admin.ch/eli/oc/2009/29/de/doc"
              },
              {
                "format": "http://publications.europa.eu/resource/authority/file-type/PDF",
                "fileUrl": "https://fedlex.data.admin.ch/filestore/fedlex.data.admin.ch/eli/oc/2009/29/de/pdf-a/fedlex-data-admin-ch-eli-oc-2009-29-de-pdf-a.pdf",
                "uri": "https://fedlex.data.admin.ch/eli/oc/2009/29/de/pdf-a"
              }
            ],
            "memorialLabel": "AS 2009 183",
            "title": "Verordnung des EJPD über Messmittel für Geschwindigkeitskontrollen und Rotlichtüberwachungen im Strassenverkehr (Geschwindigkeitsmessmittel-Verordnung)"
          },
          "http://publications.europa.eu/resource/authority/language/FRA": {
            "manifestation": [
              {
                "format": "http://publications.europa.eu/resource/authority/file-type/PDF",
                "fileUrl": "https://fedlex.data.admin.ch/filestore/fedlex.data.admin.ch/eli/oc/2009/29/fr/pdf-a/fedlex-data-admin-ch-eli-oc-2009-29-fr-pdf-a.pdf",
                "uri": "https://fedlex.data.admin.ch/eli/oc/2009/29/fr/pdf-a"
              },
              {
                "format": "http://publications.europa.eu/resource/authority/file-type/DOC",
                "fileUrl": "https://fedlex.data.admin.ch/filestore/fedlex.data.admin.ch/eli/oc/2009/29/fr/doc/fedlex-data-admin-ch-eli-oc-2009-29-fr-doc.doc",
                "uri": "https://fedlex.data.admin.ch/eli/oc/2009/29/fr/doc"
              }
            ],
            "memorialLabel": "RO 2009 183",
            "title": "Ordonnance du DFJP sur les instruments de mesure utilisés pour le contrôle de la vitesse et la surveillance de la circulation routière aux feux rouges (Ordonnance sur les instruments de mesure de vitesse)"
          },
          "http://publications.europa.eu/resource/authority/language/ITA": {
            "manifestation": [
              {
                "format": "http://publications.europa.eu/resource/authority/file-type/PDF",
                "fileUrl": "https://fedlex.data.admin.ch/filestore/fedlex.data.admin.ch/eli/oc/2009/29/it/pdf-a/fedlex-data-admin-ch-eli-oc-2009-29-it-pdf-a.pdf",
                "uri": "https://fedlex.data.admin.ch/eli/oc/2009/29/it/pdf-a"
              },
              {
                "format": "http://publications.europa.eu/resource/authority/file-type/DOC",
                "fileUrl": "https://fedlex.data.admin.ch/filestore/fedlex.data.admin.ch/eli/oc/2009/29/it/doc/fedlex-data-admin-ch-eli-oc-2009-29-it-doc.doc",
                "uri": "https://fedlex.data.admin.ch/eli/oc/2009/29/it/doc"
              }
            ],
            "memorialLabel": "RU 2009 183",
            "title": "Ordinanza del DFGP sugli strumenti di misurazione per i controlli della velocità e la sorveglianza della fase rossa ai semafori nella circolazione stradale (Ordinanza sugli strumenti di misurazione della velocità)"
          }
        },
        "responsibilityOf": "https://fedlex.data.admin.ch/vocabulary/legal-institution/33",
        "processType": "https://fedlex.data.admin.ch/vocabulary/type-procedure/ord",
        "uri": "https://fedlex.data.admin.ch/eli/oc/2009/29"
      }
    ],
    "classifiedByTaxonomyEntryLabel_raw": "941.261",
    "consolidationAbstract": {
      "typeDocumentBroader": "https://fedlex.data.admin.ch/vocabulary/resource-type/47",
      "basicAct": "https://fedlex.data.admin.ch/eli/oc/2009/29",
      "typeDocument": "https://fedlex.data.admin.ch/vocabulary/resource-type/26",
      "titles": {
        "http://publications.europa.eu/resource/authority/language/DEU": {
          "titleAlternative": "Geschwindigkeitsmessmittel-Verordnung",
          "title": "Verordnung des EJPD vom 28. November 2008 über Messmittel für Geschwindigkeitskontrollen und Rotlichtüberwachungen im Strassenverkehr (Geschwindigkeitsmessmittel-Verordnung)"
        },
        "http://publications.europa.eu/resource/authority/language/FRA": {
          "titleAlternative": "Ordonnance sur les instruments de mesure de vitesse",
          "title": "Ordonnance du DFJP du 28 novembre 2008 sur les instruments de mesure utilisés pour le contrôle de la vitesse et la surveillance de la circulation routière aux feux rouges (Ordonnance sur les instruments de mesure de vitesse)"
        },
        "http://publications.europa.eu/resource/authority/language/ITA": {
          "titleAlternative": "Ordinanza sugli strumenti di misurazione della velocità",
          "title": "Ordinanza del DFGP del 28 novembre 2008 sugli strumenti di misurazione per i controlli della velocità e la sorveglianza della fase rossa ai semafori nella circolazione stradale (Ordinanza sugli strumenti di misurazione della velocità)"
        }
      }
    },
    "classifiedByTaxonomyEntry": "https://fedlex.data.admin.ch/vocabulary/legal-taxonomy/11203",
    "classifiedByTaxonomyEntryLabel_sort": "00941.00261",
    "theme": {
      "themeId": "9",
      "themeUri": "https://fedlex.data.admin.ch/vocabulary/legal-taxonomy/10385"
    },
    "impacts": [
      {
        "impactDate": "2009-03-31",
        "informationSource": "https://fedlex.data.admin.ch/vocabulary/information-source/data-from-geschaeftsstaende",
        "fromAct": "https://fedlex.data.admin.ch/eli/oc/2009/29",
        "language": [
          "http://publications.europa.eu/resource/authority/language/ITA"
        ],
        "impactType": "https://fedlex.data.admin.ch/vocabulary/impact-type/5",
        "decisionDate": "2009-03-31",
        "historicalImpact": false
      },
      {
        "impactDate": "2009-03-31",
        "informationSource": "https://fedlex.data.admin.ch/vocabulary/information-source/data-from-geschaeftsstaende",
        "fromAct": "https://fedlex.data.admin.ch/eli/oc/2009/29",
        "language": [
          "http://publications.europa.eu/resource/authority/language/DEU"
        ],
        "impactType": "https://fedlex.data.admin.ch/vocabulary/impact-type/5",
        "decisionDate": "2009-03-31",
        "historicalImpact": false
      },
      {
        "impactDate": "2009-03-31",
        "informationSource": "https://fedlex.data.admin.ch/vocabulary/information-source/data-from-geschaeftsstaende",
        "fromAct": "https://fedlex.data.admin.ch/eli/oc/2009/29",
        "language": [
          "http://publications.europa.eu/resource/authority/language/FRA"
        ],
        "impactType": "https://fedlex.data.admin.ch/vocabulary/impact-type/5",
        "decisionDate": "2009-03-31",
        "historicalImpact": false
      }
    ],
    "classifiedByTaxonomyEntryLabel": {
      "de": "SR 941.261",
      "fr": "RS 941.261",
      "it": "RS 941.261"
    }
  },
  "timestampms": null
}
