{
  "data": {
    "uri": "https://fedlex.data.admin.ch/eli/cc/1974/2004_2004_2004/19741214",
    "type": [
      "Consolidation",
      "Work"
    ],
    "attributes": {
      "dateEndApplicability": {
        "xsd:date": "2001-08-31"
      },
      "isMemberOf": {
        "rdfs:Resource": "https://fedlex.data.admin.ch/eli/cc/1974/2004_2004_2004"
      },
      "dateApplicability": {
        "xsd:date": "1974-12-14"
      }
    },
    "references": {
      "isRealizedBy": [
        "https://fedlex.data.admin.ch/eli/cc/1974/2004_2004_2004/19741214/en",
        "https://fedlex.data.admin.ch/eli/cc/1974/2004_2004_2004/19741214/rm",
        "https://fedlex.data.admin.ch/eli/cc/1974/2004_2004_2004/19741214/it",
        "https://fedlex.data.admin.ch/eli/cc/1974/2004_2004_2004/19741214/de",
        "https://fedlex.data.admin.ch/eli/cc/1974/2004_2004_2004/19741214/fr"
      ]
    }
  },
  "included": [
    {
      "uri": "https://fedlex.data.admin.ch/eli/cc/1974/2004_2004_2004/19741214/en",
      "type": "Expression",
      "references": {
        "language": "http://publications.europa.eu/resource/authority/language/ENG"
      },
      "attributes": {
        "title": {
          "xsd:string": "Consolidation: 0.351.916.32 - 1974-12-14"
        }
      }
    },
    {
      "uri": "https://fedlex.data.admin.ch/eli/cc/1974/2004_2004_2004/19741214/rm",
      "type": "Expression",
      "references": {
        "language": "http://publications.europa.eu/resource/authority/language/ROH"
      },
      "attributes": {
        "title": {
          "xsd:string": "Consolidation: 0.351.916.32 - 1974-12-14"
        }
      }
    },
    {
      "uri": "https://fedlex.data.admin.ch/eli/cc/1974/2004_2004_2004/19741214/it",
      "type": "Expression",
      "references": {
        "language": "http://publications.europa.eu/resource/authority/language/ITA"
      },
      "attributes": {
        "title": {
          "xsd:string": "Consolidation: 0.351.916.32 - 1974-12-14"
        }
      }
    },
    {
      "uri": "https://fedlex.data.admin.ch/eli/cc/1974/2004_2004_2004/19741214/de",
      "type": "Expression",
      "references": {
        "language": "http://publications.europa.eu/resource/authority/language/DEU"
      },
      "attributes": {
        "title": {
          "xsd:string": "Consolidation: 0.351.916.32 - 1974-12-14"
        }
      }
    },
    {
      "uri": "https://fedlex.data.admin.ch/eli/cc/1974/2004_2004_2004/19741214/fr",
      "type": "Expression",
      "references": {
        "language": "http://publications.europa.eu/resource/authority/language/FRA"
      },
      "attributes": {
        "title": {
          "xsd:string": "Consolidation: 0.351.916.32 - 1974-12-14"
        }
      }
    },
    {
      "uri": "http://publications.europa.eu/resource/authority/language/ENG",
      "type": [
        "Concept",
        "Language"
      ]
    },
    {
      "uri": "http://publications.europa.eu/resource/authority/language/ROH",
      "type": [
        "Concept",
        "Language"
      ]
    },
    {
      "uri": "http://publications.europa.eu/resource/authority/language/ITA",
      "type": [
        "Concept",
        "Language"
      ]
    },
    {
      "uri": "http://publications.europa.eu/resource/authority/language/DEU",
      "type": [
        "Concept",
        "Language"
      ]
    },
    {
      "uri": "http://publications.europa.eu/resource/authority/language/FRA",
      "type": [
        "Concept",
        "Language"
      ]
    }
  ],
  "graph": "https://fedlex.data.admin.ch/eli/cc/1974/2004_2004_2004/19741214/graph",
  "facets": {
    "consolidates": [
      {
        "dateDocument": "1972-06-13",
        "expression": {
          "http://publications.europa.eu/resource/authority/language/DEU": {
            "memorialLabel": "AS 1974 2004",
            "title": "Vertrag vom 13. Juni 1972 zwischen der Schweizerischen Eidgenossenschaft und der Republik Österreich über die Ergänzung des Europäischen Übereinkommens über die Rechtshilfe in Strafsachen vom 20. April 1959 und die Erleichterung seiner Anwendung (mit Verzeichnis) "
          },
          "http://publications.europa.eu/resource/authority/language/FRA": {
            "memorialLabel": "RO 1974 2004",
            "title": "Accord du 13 juin 1972 entre la Confédération suisse et la République d'Autriche en vue de compléter la Convention européenne d'entraide judiciaire en matière pénale du 20 avril 1959 et de faciliter son application (avec liste) "
          },
          "http://publications.europa.eu/resource/authority/language/ITA": {
            "memorialLabel": "RU 1974 2004",
            "title": "Accordo del 13 giugno 1972 tra la Confederazione Svizzera e la Repubblica d'Austria che completa la Convenzione europea di assistenza giudiziaria in materia penale del 20 aprile 1959 e ne agevola l'applicazione (con Elenco) "
          }
        },
        "responsibilityOf": "https://fedlex.data.admin.ch/vocabulary/legal-institution/5",
        "processType": "https://fedlex.data.admin.ch/vocabulary/type-procedure/ord",
        "uri": "https://fedlex.data.admin.ch/eli/oc/1974/2004_2004_2004"
      }
    ],
    "classifiedByTaxonomyEntryLabel_raw": "0.351.916.32",
    "consolidationAbstract": {
      "typeDocumentBroader": "https://fedlex.data.admin.ch/vocabulary/resource-type/49",
      "basicAct": "https://fedlex.data.admin.ch/eli/oc/1974/2004_2004_2004",
      "typeDocument": "https://fedlex.data.admin.ch/vocabulary/resource-type/31",
      "titles": {
        "http://publications.europa.eu/resource/authority/language/DEU": {
          "title": "Vertrag vom 13. Juni 1972 zwischen der Schweizerischen Eidgenossenschaft und der Republik Österreich über die Ergänzung des Europäischen Übereinkommens über die Rechtshilfe in Strafsachen vom 20. April 1959 und die Erleichterung seiner Anwendung (mit Verzeichnis) "
        },
        "http://publications.europa.eu/resource/authority/language/FRA": {
          "title": "Accord du 13 juin 1972 entre la Confédération suisse et la République d'Autriche en vue de compléter la Convention européenne d'entraide judiciaire en matière pénale du 20 avril 1959 et de faciliter son application (avec liste) "
        },
        "http://publications.europa.eu/resource/authority/language/ITA": {
          "title": "Accordo del 13 giugno 1972 tra la Confederazione Svizzera e la Repubblica d'Austria che completa la Convenzione europea di assistenza giudiziaria in materia penale del 20 aprile 1959 e ne agevola l'applicazione (con Elenco) "
        }
      }
    },
    "classifiedByTaxonomyEntry": "https://fedlex.data.admin.ch/vocabulary/legal-taxonomy/1368",
    "classifiedByTaxonomyEntryLabel_sort": "00000.00351.00916.00032",
    "theme": {
      "themeId": "0.3",
      "themeUri": "https://fedlex.data.admin.ch/vocabulary/legal-taxonomy/1291"
    },
    "impacts": [
      {
        "impactDate": "1974-12-14",
        "informationSource": "https://fedlex.data.admin.ch/vocabulary/information-source/data-from-geschaeftsstaende",
        "fromAct": "https://fedlex.data.admin.ch/eli/oc/1974/2004_2004_2004",
        "language": [
          "http://publications.europa.eu/resource/authority/language/ITA"
        ],
        "impactType": "https://fedlex.data.admin.ch/vocabulary/impact-type/5",
        "decisionDate": "1974-12-14",
        "historicalImpact": false
      },
      {
        "impactDate": "1974-12-14",
        "informationSource": "https://fedlex.data.admin.ch/vocabulary/information-source/data-from-geschaeftsstaende",
        "fromAct": "https://fedlex.data.admin.ch/eli/oc/1974/2004_2004_2004",
        "language": [
          "http://publications.europa.eu/resource/authority/language/FRA"
        ],
        "impactType": "https://fedlex.data.admin.ch/vocabulary/impact-type/5",
        "decisionDate": "1974-12-14",
        "historicalImpact": false
      },
      {
        "impactDate": "1974-12-14",
        "informationSource": "https://fedlex.data.admin.ch/vocabulary/information-source/data-from-geschaeftsstaende",
        "fromAct": "https://fedlex.data.admin.ch/eli/oc/1974/2004_2004_2004",
        "language": [
          "http://publications.europa.eu/resource/authority/language/DEU"
        ],
        "impactType": "https://fedlex.data.admin.ch/vocabulary/impact-type/5",
        "decisionDate": "1974-12-14",
        "historicalImpact": false
      }
    ],
    "classifiedByTaxonomyEntryLabel": {
      "de": "SR 0.351.916.32",
      "fr": "RS 0.351.916.32",
      "it": "RS 0.351.916.32"
    }
  },
  "timestampms": null
}
