{
  "data": {
    "uri": "https://fedlex.data.admin.ch/eli/cc/1994/2859_2859_2859/19990301",
    "type": [
      "Consolidation",
      "Work"
    ],
    "attributes": {
      "created": {
        "xsd:dateTime": [
          "1999-02-28T23:00:00.000Z"
        ]
      },
      "dateEndApplicability": {
        "xsd:date": "2001-12-31"
      },
      "modified": {
        "xsd:dateTime": [
          "1999-02-28T23:00:00.000Z"
        ]
      },
      "isMemberOf": {
        "rdfs:Resource": "https://fedlex.data.admin.ch/eli/cc/1994/2859_2859_2859"
      },
      "dateApplicability": {
        "xsd:date": "1999-03-01"
      }
    },
    "references": {
      "isRealizedBy": [
        "https://fedlex.data.admin.ch/eli/cc/1994/2859_2859_2859/19990301/de",
        "https://fedlex.data.admin.ch/eli/cc/1994/2859_2859_2859/19990301/it",
        "https://fedlex.data.admin.ch/eli/cc/1994/2859_2859_2859/19990301/rm",
        "https://fedlex.data.admin.ch/eli/cc/1994/2859_2859_2859/19990301/fr",
        "https://fedlex.data.admin.ch/eli/cc/1994/2859_2859_2859/19990301/en"
      ]
    }
  },
  "included": [
    {
      "uri": "https://fedlex.data.admin.ch/eli/cc/1994/2859_2859_2859/19990301/de",
      "type": "Expression",
      "references": {
        "language": "http://publications.europa.eu/resource/authority/language/DEU"
      },
      "attributes": {
        "title": {
          "xsd:string": "Consolidation: 142.215 - 1999-03-01"
        }
      }
    },
    {
      "uri": "https://fedlex.data.admin.ch/eli/cc/1994/2859_2859_2859/19990301/it",
      "type": "Expression",
      "references": {
        "language": "http://publications.europa.eu/resource/authority/language/ITA"
      },
      "attributes": {
        "title": {
          "xsd:string": "Consolidation: 142.215 - 1999-03-01"
        }
      }
    },
    {
      "uri": "https://fedlex.data.admin.ch/eli/cc/1994/2859_2859_2859/19990301/rm",
      "type": "Expression",
      "references": {
        "language": "http://publications.europa.eu/resource/authority/language/ROH"
      },
      "attributes": {
        "title": {
          "xsd:string": "Consolidation: 142.215 - 1999-03-01"
        }
      }
    },
    {
      "uri": "https://fedlex.data.admin.ch/eli/cc/1994/2859_2859_2859/19990301/fr",
      "type": "Expression",
      "references": {
        "language": "http://publications.europa.eu/resource/authority/language/FRA"
      },
      "attributes": {
        "title": {
          "xsd:string": "Consolidation: 142.215 - 1999-03-01"
        }
      }
    },
    {
      "uri": "https://fedlex.data.admin.ch/eli/cc/1994/2859_2859_2859/19990301/en",
      "type": "Expression",
      "references": {
        "language": "http://publications.europa.eu/resource/authority/language/ENG"
      },
      "attributes": {
        "title": {
          "xsd:string": "Consolidation: 142.215 - 1999-03-01"
        }
      }
    },
    {
      "uri": "http://publications.europa.eu/resource/authority/language/DEU",
      "type": [
        "Concept",
        "Language"
      ]
    },
    {
      "uri": "http://publications.europa.eu/resource/authority/language/ITA",
      "type": [
        "Concept",
        "Language"
      ]
    },
    {
      "uri": "http://publications.europa.eu/resource/authority/language/ROH",
      "type": [
        "Concept",
        "Language"
      ]
    },
    {
      "uri": "http://publications.europa.eu/resource/authority/language/FRA",
      "type": [
        "Concept",
        "Language"
      ]
    },
    {
      "uri": "http://publications.europa.eu/resource/authority/language/ENG",
      "type": [
        "Concept",
        "Language"
      ]
    }
  ],
  "facets": {
    "consolidates": [
      {
        "dateDocument": "1999-02-17",
        "expression": {
          "http://publications.europa.eu/resource/authority/language/DEU": {
            "manifestation": [
              {
                "format": "http://publications.europa.eu/resource/authority/file-type/PDF",
                "fileUrl": "https://fedlex.data.admin.ch/filestore/fedlex.data.admin.ch/eli/oc/1999/169/de/pdf-a/fedlex-data-admin-ch-eli-oc-1999-169-de-pdf-a.pdf",
                "uri": "https://fedlex.data.admin.ch/eli/oc/1999/169/de/pdf-a"
              },
              {
                "format": "http://publications.europa.eu/resource/authority/file-type/DOC",
                "fileUrl": "https://fedlex.data.admin.ch/filestore/fedlex.data.admin.ch/eli/oc/1999/169/de/doc/fedlex-data-admin-ch-eli-oc-1999-169-de-doc.doc",
                "uri": "https://fedlex.data.admin.ch/eli/oc/1999/169/de/doc"
              }
            ],
            "memorialLabel": "AS 1999 1240",
            "title": "Verordnung über das Zentrale Ausländerregister (ZAR-Verordnung)"
          },
          "http://publications.europa.eu/resource/authority/language/FRA": {
            "manifestation": [
              {
                "format": "http://publications.europa.eu/resource/authority/file-type/DOC",
                "fileUrl": "https://fedlex.data.admin.ch/filestore/fedlex.data.admin.ch/eli/oc/1999/169/fr/doc/fedlex-data-admin-ch-eli-oc-1999-169-fr-doc.doc",
                "uri": "https://fedlex.data.admin.ch/eli/oc/1999/169/fr/doc"
              },
              {
                "format": "http://publications.europa.eu/resource/authority/file-type/PDF",
                "fileUrl": "https://fedlex.data.admin.ch/filestore/fedlex.data.admin.ch/eli/oc/1999/169/fr/pdf-a/fedlex-data-admin-ch-eli-oc-1999-169-fr-pdf-a.pdf",
                "uri": "https://fedlex.data.admin.ch/eli/oc/1999/169/fr/pdf-a"
              }
            ],
            "memorialLabel": "RO 1999 1240",
            "title": "Ordonnance sur le Registre central des étrangers (Ordonnance RCE)"
          },
          "http://publications.europa.eu/resource/authority/language/ITA": {
            "manifestation": [
              {
                "format": "http://publications.europa.eu/resource/authority/file-type/DOC",
                "fileUrl": "https://fedlex.data.admin.ch/filestore/fedlex.data.admin.ch/eli/oc/1999/169/it/doc/fedlex-data-admin-ch-eli-oc-1999-169-it-doc.doc",
                "uri": "https://fedlex.data.admin.ch/eli/oc/1999/169/it/doc"
              },
              {
                "format": "http://publications.europa.eu/resource/authority/file-type/PDF",
                "fileUrl": "https://fedlex.data.admin.ch/filestore/fedlex.data.admin.ch/eli/oc/1999/169/it/pdf-a/fedlex-data-admin-ch-eli-oc-1999-169-it-pdf-a.pdf",
                "uri": "https://fedlex.data.admin.ch/eli/oc/1999/169/it/pdf-a"
              }
            ],
            "memorialLabel": "RU 1999 1240",
            "title": "Ordinanza sul Registro centrale degli stramieri (Ordinanza RCS)"
          }
        },
        "responsibilityOf": "https://fedlex.data.admin.ch/vocabulary/legal-institution/41",
        "processType": "https://fedlex.data.admin.ch/vocabulary/type-procedure/ord",
        "uri": "https://fedlex.data.admin.ch/eli/oc/1999/169"
      }
    ],
    "classifiedByTaxonomyEntryLabel_raw": "142.215",
    "consolidationAbstract": {
      "typeDocumentBroader": "https://fedlex.data.admin.ch/vocabulary/resource-type/47",
      "dateNoLongerInForce": "2006-05-29",
      "basicAct": "https://fedlex.data.admin.ch/eli/oc/1994/2859_2859_2859",
      "typeDocument": "https://fedlex.data.admin.ch/vocabulary/resource-type/29",
      "titles": {
        "http://publications.europa.eu/resource/authority/language/DEU": {
          "titleAlternative": "ZAR-Verordnung",
          "title": "Verordnung vom 23. November 1994 über das Zentrale Ausländerregister (ZAR-Verordnung)"
        },
        "http://publications.europa.eu/resource/authority/language/FRA": {
          "titleAlternative": "Ordonnance RCE",
          "title": "Ordonnance du 23 novembre 1994 sur le Registre central des étrangers (Ordonnance RCE)"
        },
        "http://publications.europa.eu/resource/authority/language/ITA": {
          "titleAlternative": "Ordinanza RCS",
          "title": "Ordinanza del 23 novembre 1994 sul Registro centrale degli stranieri (Ordinanza RCS)"
        }
      }
    },
    "classifiedByTaxonomyEntry": "https://fedlex.data.admin.ch/vocabulary/legal-taxonomy/4862",
    "classifiedByTaxonomyEntryLabel_sort": "142.215",
    "theme": {
      "themeId": "1",
      "themeUri": "https://fedlex.data.admin.ch/vocabulary/legal-taxonomy/4713"
    },
    "impacts": [
      {
        "impactDate": "1999-03-01",
        "commentFrom": {
          "fr": "O 17.02.1999 (I)"
        },
        "informationSource": "https://fedlex.data.admin.ch/vocabulary/information-source/data-from-mutation",
        "commentTo": {
          "fr": "Préamb.; art. 2 à 9, 9<i>a</i>, 14, 17, 20"
        },
        "fromAct": "https://fedlex.data.admin.ch/eli/oc/1999/169",
        "language": [
          "http://publications.europa.eu/resource/authority/language/FRA"
        ],
        "impactType": "https://fedlex.data.admin.ch/vocabulary/impact-type/1",
        "historicalImpact": false
      },
      {
        "impactDate": "1999-03-01",
        "commentFrom": {
          "it": "O 17.02.1999 (I)"
        },
        "informationSource": "https://fedlex.data.admin.ch/vocabulary/information-source/data-from-mutation",
        "commentTo": {
          "it": "ingr.; art. 2-9, 9<i>a</i>, 14, 17, 20"
        },
        "fromAct": "https://fedlex.data.admin.ch/eli/oc/1999/169",
        "language": [
          "http://publications.europa.eu/resource/authority/language/ITA"
        ],
        "impactType": "https://fedlex.data.admin.ch/vocabulary/impact-type/1",
        "historicalImpact": false
      },
      {
        "impactDate": "1999-03-01",
        "commentFrom": {
          "it": "I, II"
        },
        "informationSource": "https://fedlex.data.admin.ch/vocabulary/information-source/data-from-geschaeftsstaende",
        "fromAct": "https://fedlex.data.admin.ch/eli/oc/1999/169",
        "language": [
          "http://publications.europa.eu/resource/authority/language/ITA"
        ],
        "impactType": "https://fedlex.data.admin.ch/vocabulary/impact-type/1",
        "decisionDate": "1999-02-17",
        "historicalImpact": false
      },
      {
        "impactDate": "1999-03-01",
        "commentFrom": {
          "de": "V 17.02.1999 (I)"
        },
        "informationSource": "https://fedlex.data.admin.ch/vocabulary/information-source/data-from-mutation",
        "commentTo": {
          "de": "Ingr.; Art. 2-9, 9<i>a</i>, 14, 17, 20"
        },
        "fromAct": "https://fedlex.data.admin.ch/eli/oc/1999/169",
        "language": [
          "http://publications.europa.eu/resource/authority/language/DEU"
        ],
        "impactType": "https://fedlex.data.admin.ch/vocabulary/impact-type/1",
        "historicalImpact": false
      },
      {
        "impactDate": "1999-03-01",
        "commentFrom": {
          "de": "I, II"
        },
        "informationSource": "https://fedlex.data.admin.ch/vocabulary/information-source/data-from-geschaeftsstaende",
        "fromAct": "https://fedlex.data.admin.ch/eli/oc/1999/169",
        "language": [
          "http://publications.europa.eu/resource/authority/language/DEU"
        ],
        "impactType": "https://fedlex.data.admin.ch/vocabulary/impact-type/1",
        "decisionDate": "1999-02-17",
        "historicalImpact": false
      },
      {
        "impactDate": "1999-03-01",
        "commentFrom": {
          "fr": "I, II"
        },
        "informationSource": "https://fedlex.data.admin.ch/vocabulary/information-source/data-from-geschaeftsstaende",
        "fromAct": "https://fedlex.data.admin.ch/eli/oc/1999/169",
        "language": [
          "http://publications.europa.eu/resource/authority/language/FRA"
        ],
        "impactType": "https://fedlex.data.admin.ch/vocabulary/impact-type/1",
        "decisionDate": "1999-02-17",
        "historicalImpact": false
      }
    ],
    "classifiedByTaxonomyEntryLabel": {
      "de": "SR 142.215",
      "fr": "RS 142.215",
      "it": "RS 142.215"
    }
  },
  "graph": "https://fedlex.data.admin.ch/eli/cc/1994/2859_2859_2859/19990301/graph",
  "timestampms": null
}
