{
  "data": {
    "uri": "https://fedlex.data.admin.ch/eli/fga/1853/3__215_",
    "type": [
      "Act",
      "Work"
    ],
    "attributes": {
      "created": {
        "xsd:dateTime": [
          "1853-08-05T23:30:14.000Z"
        ]
      },
      "modified": {
        "xsd:dateTime": [
          "1853-08-05T23:30:14.000Z"
        ]
      },
      "typeDocument": {
        "rdfs:Resource": "http://example.com"
      },
      "publicationDate": {
        "xsd:date": "1853-08-06"
      }
    },
    "references": {
      "isRealizedBy": [
        "https://fedlex.data.admin.ch/eli/fga/1853/3__215_/fr"
      ],
      "isPartOf": "https://fedlex.data.admin.ch/eli/collection/fga/1853/36"
    }
  },
  "included": [
    {
      "uri": "https://fedlex.data.admin.ch/eli/fga/1853/3__215_/fr",
      "type": "Expression",
      "references": {
        "isEmbodiedBy": [
          "https://fedlex.data.admin.ch/eli/fga/1853/3__215_/fr/pdf-a"
        ],
        "language": "http://publications.europa.eu/resource/authority/language/FRA"
      },
      "attributes": {
        "memorialName": {
          "xsd:string": "FF"
        },
        "memorialPageTo": {
          "xsd:int": 236
        },
        "memorialPage": {
          "xsd:int": 215
        },
        "isPartOf": {
          "rdfs:Resource": "https://fedlex.data.admin.ch/eli/collection/fga/1853/36/fr"
        },
        "memorialYear": {
          "xsd:int": 1853
        },
        "title": {
          "xsd:string": "MESSAGE du Conseil fédéral suisse aux deux Conseils législatifs de la Confédération relativement à la navigation sur le lac de Constance et le Rhin. (Du 1 Mai 1853)"
        }
      }
    },
    {
      "uri": "https://fedlex.data.admin.ch/eli/collection/fga/1853/36",
      "type": [
        "Memorial",
        "Work"
      ]
    },
    {
      "uri": "https://fedlex.data.admin.ch/eli/fga/1853/3__215_/fr/pdf-a",
      "type": "Manifestation",
      "references": {
        "rightsHolder": "https://fedlex.data.admin.ch/vocabulary/legal-institution/2",
        "publisher": "https://fedlex.data.admin.ch/vocabulary/legal-institution/2"
      },
      "attributes": {
        "isExemplifiedByPrivate": {
          "rdfs:Resource": "https://www.amtsdruckschriften.bar.admin.ch/viewOrigDoc.do?id=10056432&action=open"
        },
        "userFormat": {
          "rdfs:Resource": "https://fedlex.data.admin.ch/vocabulary/user-format/pdf-a"
        },
        "format": {
          "rdfs:Resource": "http://publications.europa.eu/resource/authority/file-type/PDF"
        },
        "isExemplifiedBy": {
          "rdfs:Resource": "https://www.amtsdruckschriften.bar.admin.ch/viewOrigDoc.do?id=10056432&action=open"
        }
      }
    },
    {
      "uri": "http://publications.europa.eu/resource/authority/language/FRA",
      "type": [
        "Concept",
        "Language"
      ]
    },
    {
      "uri": "https://fedlex.data.admin.ch/vocabulary/legal-institution/2",
      "type": [
        "Concept",
        "LegalInstitution"
      ]
    }
  ],
  "graph": "https://fedlex.data.admin.ch/eli/fga/1853/3__215_/graph",
  "facets": {
    "sortingDateTime": "1853-08-05T23:30:14Z",
    "sortingDate": "1853-08-06",
    "memorialLabel": {
      "http://publications.europa.eu/resource/authority/language/FRA": "FF 1853 III 215"
    },
    "memorialPage": {
      "http://publications.europa.eu/resource/authority/language/FRA": 215
    },
    "title": {
      "fr": "MESSAGE du Conseil fédéral suisse aux deux Conseils législatifs de la Confédération relativement à la navigation sur le lac de Constance et le Rhin. (Du 1 Mai 1853)"
    }
  },
  "timestampms": null
}
