{
  "data": {
    "uri": "https://fedlex.data.admin.ch/eli/dl/proj/7022/0010",
    "type": [
      "Draft",
      "Event",
      "InitialDraft"
    ],
    "attributes": {
      "parliamentDraftId": {
        "xsd:string": [
          "22.048"
        ]
      },
      "hasResultingLegalResource": {
        "rdfs:Resource": [
          "https://fedlex.data.admin.ch/eli/fga/2022/1377",
          "https://fedlex.data.admin.ch/eli/fga/2022/1366",
          "https://fedlex.data.admin.ch/eli/fga/2022/1378",
          "https://fedlex.data.admin.ch/eli/fga/2022/1367",
          "https://fedlex.data.admin.ch/eli/fga/2022/1375",
          "https://fedlex.data.admin.ch/eli/fga/2022/1376",
          "https://fedlex.data.admin.ch/eli/fga/2022/1368",
          "https://fedlex.data.admin.ch/eli/fga/2022/1369",
          "https://fedlex.data.admin.ch/eli/oc/2023/103",
          "https://fedlex.data.admin.ch/eli/fga/2022/1370",
          "https://fedlex.data.admin.ch/eli/oc/2023/104",
          "https://fedlex.data.admin.ch/eli/oc/2023/105",
          "https://fedlex.data.admin.ch/eli/fga/2022/1373",
          "https://fedlex.data.admin.ch/eli/fga/2022/1374",
          "https://fedlex.data.admin.ch/eli/fga/2022/1371",
          "https://fedlex.data.admin.ch/eli/fga/2022/1372"
        ]
      }
    },
    "references": {
      "draftHasLegislativeTask": [
        "https://fedlex.data.admin.ch/eli/dl/proj/7022/0010/event/1",
        "https://fedlex.data.admin.ch/eli/dl/proj/7022/0010/event/2",
        "https://fedlex.data.admin.ch/eli/dl/proj/7022/0010/event/3"
      ]
    }
  },
  "included": [
    {
      "uri": "https://fedlex.data.admin.ch/eli/dl/proj/7022/0010/event/1",
      "type": [
        "Event",
        "LegislativeTask"
      ],
      "attributes": {
        "legislativeTaskType": {
          "rdfs:Resource": "https://fedlex.data.admin.ch/vocabulary/type-projet/8"
        },
        "legislativeTaskHasResultingLegalResource": {
          "rdfs:Resource": "https://fedlex.data.admin.ch/eli/fga/2021/2861"
        },
        "decisionDate": {
          "xsd:date": "2021-12-10"
        }
      }
    },
    {
      "uri": "https://fedlex.data.admin.ch/eli/dl/proj/7022/0010/event/2",
      "type": [
        "Event",
        "LegislativeTask"
      ],
      "attributes": {
        "legislativeTaskType": {
          "rdfs:Resource": "https://fedlex.data.admin.ch/vocabulary/type-projet/200"
        },
        "legislativeTaskHasResultingLegalResource": {
          "rdfs:Resource": "https://fedlex.data.admin.ch/eli/fga/2022/1366"
        },
        "decisionDate": {
          "xsd:date": "2022-05-18"
        }
      }
    },
    {
      "uri": "https://fedlex.data.admin.ch/eli/dl/proj/7022/0010/event/3",
      "type": [
        "Event",
        "LegislativeTask"
      ],
      "attributes": {
        "legislativeTaskType": {
          "rdfs:Resource": "https://fedlex.data.admin.ch/vocabulary/type-projet/1"
        },
        "legislativeTaskHasResultingLegalResource": {
          "rdfs:Resource": "https://fedlex.data.admin.ch/eli/dl/proj/2021/94/cons_1"
        }
      }
    }
  ],
  "graph": "https://fedlex.data.admin.ch/eli/dl/proj/7022/0010/graph",
  "facets": {
    "resultingActs": [
      {
        "dateDocument": "2021-12-10",
        "responsibilityOf": "https://fedlex.data.admin.ch/vocabulary/legal-institution/2",
        "memorialLabel": {
          "http://publications.europa.eu/resource/authority/language/DEU": "BBl 2021 2861",
          "http://publications.europa.eu/resource/authority/language/FRA": "FF 2021 2861",
          "http://publications.europa.eu/resource/authority/language/ITA": "FF 2021 2861"
        },
        "typeDocument": "https://fedlex.data.admin.ch/vocabulary/resource-type/40",
        "uri": "https://fedlex.data.admin.ch/eli/fga/2021/2861"
      },
      {
        "dateDocument": "2022-05-18",
        "responsibilityOf": "https://fedlex.data.admin.ch/vocabulary/legal-institution/195",
        "memorialLabel": {
          "http://publications.europa.eu/resource/authority/language/DEU": "BBl 2022 1366",
          "http://publications.europa.eu/resource/authority/language/FRA": "FF 2022 1366",
          "http://publications.europa.eu/resource/authority/language/ITA": "FF 2022 1366"
        },
        "typeDocument": "https://fedlex.data.admin.ch/vocabulary/resource-type/23",
        "uri": "https://fedlex.data.admin.ch/eli/fga/2022/1366"
      }
    ]
  },
  "timestampms": null
}
