{
  "data": {
    "uri": "https://fedlex.data.admin.ch/eli/cc/2013/3/20240101",
    "type": [
      "Consolidation",
      "Work"
    ],
    "attributes": {
      "isMemberOf": {
        "rdfs:Resource": "https://fedlex.data.admin.ch/eli/cc/2013/3"
      },
      "dateApplicability": {
        "xsd:date": "2024-01-01"
      }
    }
  },
  "graph": "https://fedlex.data.admin.ch/eli/cc/2013/3/20240101/graph",
  "facets": {
    "classifiedByTaxonomyEntryLabel_raw": "211.432.11",
    "consolidationAbstract": {
      "typeDocumentBroader": "https://fedlex.data.admin.ch/vocabulary/resource-type/47",
      "basicAct": "https://fedlex.data.admin.ch/eli/oc/2013/3",
      "typeDocument": "https://fedlex.data.admin.ch/vocabulary/resource-type/26",
      "titles": {
        "http://publications.europa.eu/resource/authority/language/DEU": {
          "titleShort": "TGBV",
          "title": "Technische Verordnung des EJPD und des VBS vom 28. Dezember 2012 über das Grundbuch (TGBV)"
        },
        "http://publications.europa.eu/resource/authority/language/FRA": {
          "titleShort": "OTRF",
          "title": "Ordonnance technique du DFJP et du DDPS du 28 décembre 2012 concernant le registre foncier (OTRF)"
        },
        "http://publications.europa.eu/resource/authority/language/ITA": {
          "titleShort": "OTRF",
          "title": "Ordinanza tecnica del DFGP e del DDPS del 28 dicembre 2012 sul registro fondiario (OTRF)"
        }
      }
    },
    "classifiedByTaxonomyEntry": "https://fedlex.data.admin.ch/vocabulary/legal-taxonomy/5788",
    "classifiedByTaxonomyEntryLabel_sort": "00211.00432.00011",
    "theme": {
      "themeId": "2",
      "themeUri": "https://fedlex.data.admin.ch/vocabulary/legal-taxonomy/5701"
    },
    "classifiedByTaxonomyEntryLabel": {
      "de": "SR 211.432.11",
      "fr": "RS 211.432.11",
      "it": "RS 211.432.11"
    }
  },
  "timestampms": null
}
