{
  "data": {
    "uri": "https://fedlex.data.admin.ch/eli/cc/1969/484_493_491/19690701",
    "type": [
      "Consolidation",
      "Work"
    ],
    "attributes": {
      "dateEndApplicability": {
        "xsd:date": "1970-07-01"
      },
      "isMemberOf": {
        "rdfs:Resource": "https://fedlex.data.admin.ch/eli/cc/1969/484_493_491"
      },
      "dateApplicability": {
        "xsd:date": "1969-07-01"
      }
    },
    "references": {
      "isRealizedBy": [
        "https://fedlex.data.admin.ch/eli/cc/1969/484_493_491/19690701/de",
        "https://fedlex.data.admin.ch/eli/cc/1969/484_493_491/19690701/en",
        "https://fedlex.data.admin.ch/eli/cc/1969/484_493_491/19690701/rm",
        "https://fedlex.data.admin.ch/eli/cc/1969/484_493_491/19690701/it",
        "https://fedlex.data.admin.ch/eli/cc/1969/484_493_491/19690701/fr"
      ]
    }
  },
  "included": [
    {
      "uri": "https://fedlex.data.admin.ch/eli/cc/1969/484_493_491/19690701/de",
      "type": "Expression",
      "references": {
        "language": "http://publications.europa.eu/resource/authority/language/DEU"
      },
      "attributes": {
        "title": {
          "xsd:string": "Consolidation: 916.111.211 - 1969-07-01"
        }
      }
    },
    {
      "uri": "https://fedlex.data.admin.ch/eli/cc/1969/484_493_491/19690701/en",
      "type": "Expression",
      "references": {
        "language": "http://publications.europa.eu/resource/authority/language/ENG"
      },
      "attributes": {
        "title": {
          "xsd:string": "Consolidation: 916.111.211 - 1969-07-01"
        }
      }
    },
    {
      "uri": "https://fedlex.data.admin.ch/eli/cc/1969/484_493_491/19690701/rm",
      "type": "Expression",
      "references": {
        "language": "http://publications.europa.eu/resource/authority/language/ROH"
      },
      "attributes": {
        "title": {
          "xsd:string": "Consolidation: 916.111.211 - 1969-07-01"
        }
      }
    },
    {
      "uri": "https://fedlex.data.admin.ch/eli/cc/1969/484_493_491/19690701/it",
      "type": "Expression",
      "references": {
        "language": "http://publications.europa.eu/resource/authority/language/ITA"
      },
      "attributes": {
        "title": {
          "xsd:string": "Consolidation: 916.111.211 - 1969-07-01"
        }
      }
    },
    {
      "uri": "https://fedlex.data.admin.ch/eli/cc/1969/484_493_491/19690701/fr",
      "type": "Expression",
      "references": {
        "language": "http://publications.europa.eu/resource/authority/language/FRA"
      },
      "attributes": {
        "title": {
          "xsd:string": "Consolidation: 916.111.211 - 1969-07-01"
        }
      }
    },
    {
      "uri": "http://publications.europa.eu/resource/authority/language/DEU",
      "type": [
        "Concept",
        "Language"
      ]
    },
    {
      "uri": "http://publications.europa.eu/resource/authority/language/ENG",
      "type": [
        "Concept",
        "Language"
      ]
    },
    {
      "uri": "http://publications.europa.eu/resource/authority/language/ROH",
      "type": [
        "Concept",
        "Language"
      ]
    },
    {
      "uri": "http://publications.europa.eu/resource/authority/language/ITA",
      "type": [
        "Concept",
        "Language"
      ]
    },
    {
      "uri": "http://publications.europa.eu/resource/authority/language/FRA",
      "type": [
        "Concept",
        "Language"
      ]
    }
  ],
  "graph": "https://fedlex.data.admin.ch/eli/cc/1969/484_493_491/19690701/graph",
  "facets": {
    "consolidates": [
      {
        "dateDocument": "1969-07-09",
        "expression": {
          "http://publications.europa.eu/resource/authority/language/DEU": {
            "memorialLabel": "AS 1969 484",
            "title": "Bundesratsbeschluss vom 9. Juli 1969 betreffend die Übernahmepreise für Inlandgetreide der Ernte 1969"
          },
          "http://publications.europa.eu/resource/authority/language/FRA": {
            "memorialLabel": "RO 1969 493",
            "title": "Arrêté du Conseil fédéral du 9 juillet 1969 fixant le prix d'achat du blé indigène de la récolte de 1969"
          },
          "http://publications.europa.eu/resource/authority/language/ITA": {
            "memorialLabel": "RU 1969 491",
            "title": "Degreto del Consiglio federale del 9 luglio 1969 che stabilisce il prezzo d'acquisto del grano indigeno del raccolto 1969"
          }
        },
        "processType": "https://fedlex.data.admin.ch/vocabulary/type-procedure/ord",
        "uri": "https://fedlex.data.admin.ch/eli/oc/1969/484_493_491"
      }
    ],
    "consolidationAbstract": {
      "typeDocumentBroader": "https://fedlex.data.admin.ch/vocabulary/resource-type/47",
      "dateNoLongerInForce": "1970-07-01",
      "typeDocument": "https://fedlex.data.admin.ch/vocabulary/resource-type/29",
      "titles": {
        "http://publications.europa.eu/resource/authority/language/DEU": {
          "title": "Bundesratsbeschluss vom 9. Juli 1969 betreffend die Übernahmepreise für Inlandgetreide der Ernte 1969"
        },
        "http://publications.europa.eu/resource/authority/language/FRA": {
          "title": "Arrêté du Conseil fédéral du 9 juillet 1969 fixant le prix d'achat du blé indigène de la récolte de 1969"
        },
        "http://publications.europa.eu/resource/authority/language/ITA": {
          "title": "Degreto del Consiglio federale del 9 luglio 1969 che stabilisce il prezzo d'acquisto del grano indigeno del raccolto 1969"
        }
      }
    },
    "classifiedByTaxonomyEntry": "https://fedlex.data.admin.ch/vocabulary/legal-taxonomy/10497",
    "theme": {
      "themeId": "9",
      "themeUri": "https://fedlex.data.admin.ch/vocabulary/legal-taxonomy/10385"
    },
    "impacts": [
      {
        "impactDate": "1969-07-01",
        "informationSource": "https://fedlex.data.admin.ch/vocabulary/information-source/data-from-geschaeftsstaende",
        "fromAct": "https://fedlex.data.admin.ch/eli/oc/1969/484_493_491",
        "language": [
          "http://publications.europa.eu/resource/authority/language/DEU"
        ],
        "impactType": "https://fedlex.data.admin.ch/vocabulary/impact-type/5",
        "decisionDate": "1969-07-01",
        "historicalImpact": false
      },
      {
        "impactDate": "1969-07-01",
        "informationSource": "https://fedlex.data.admin.ch/vocabulary/information-source/data-from-geschaeftsstaende",
        "fromAct": "https://fedlex.data.admin.ch/eli/oc/1969/484_493_491",
        "language": [
          "http://publications.europa.eu/resource/authority/language/FRA"
        ],
        "impactType": "https://fedlex.data.admin.ch/vocabulary/impact-type/5",
        "decisionDate": "1969-07-01",
        "historicalImpact": false
      },
      {
        "impactDate": "1969-07-01",
        "informationSource": "https://fedlex.data.admin.ch/vocabulary/information-source/data-from-geschaeftsstaende",
        "fromAct": "https://fedlex.data.admin.ch/eli/oc/1969/484_493_491",
        "language": [
          "http://publications.europa.eu/resource/authority/language/ITA"
        ],
        "impactType": "https://fedlex.data.admin.ch/vocabulary/impact-type/5",
        "decisionDate": "1969-07-01",
        "historicalImpact": false
      }
    ],
    "classifiedByTaxonomyEntryLabel": {
      "de": "SR 916.111.211",
      "fr": "RS 916.111.211",
      "it": "RS 916.111.211"
    }
  },
  "timestampms": null
}
