{
  "data": {
    "uri": "https://fedlex.data.admin.ch/eli/cc/62/159_164_166/19460101",
    "type": [
      "Consolidation",
      "Work"
    ],
    "attributes": {
      "dateEndApplicability": {
        "xsd:date": "1948-02-29"
      },
      "isMemberOf": {
        "rdfs:Resource": "https://fedlex.data.admin.ch/eli/cc/62/159_164_166"
      },
      "dateApplicability": {
        "xsd:date": "1946-01-01"
      }
    },
    "references": {
      "isRealizedBy": [
        "https://fedlex.data.admin.ch/eli/cc/62/159_164_166/19460101/de",
        "https://fedlex.data.admin.ch/eli/cc/62/159_164_166/19460101/rm",
        "https://fedlex.data.admin.ch/eli/cc/62/159_164_166/19460101/it",
        "https://fedlex.data.admin.ch/eli/cc/62/159_164_166/19460101/fr",
        "https://fedlex.data.admin.ch/eli/cc/62/159_164_166/19460101/en"
      ]
    }
  },
  "included": [
    {
      "uri": "https://fedlex.data.admin.ch/eli/cc/62/159_164_166/19460101/de",
      "type": "Expression",
      "references": {
        "language": "http://publications.europa.eu/resource/authority/language/DEU"
      },
      "attributes": {
        "title": {
          "xsd:string": "Consolidation: 172.216.321 - 1946-01-01"
        }
      }
    },
    {
      "uri": "https://fedlex.data.admin.ch/eli/cc/62/159_164_166/19460101/rm",
      "type": "Expression",
      "references": {
        "language": "http://publications.europa.eu/resource/authority/language/ROH"
      },
      "attributes": {
        "title": {
          "xsd:string": "Consolidation: 172.216.321 - 1946-01-01"
        }
      }
    },
    {
      "uri": "https://fedlex.data.admin.ch/eli/cc/62/159_164_166/19460101/it",
      "type": "Expression",
      "references": {
        "language": "http://publications.europa.eu/resource/authority/language/ITA"
      },
      "attributes": {
        "title": {
          "xsd:string": "Consolidation: 172.216.321 - 1946-01-01"
        }
      }
    },
    {
      "uri": "https://fedlex.data.admin.ch/eli/cc/62/159_164_166/19460101/fr",
      "type": "Expression",
      "references": {
        "language": "http://publications.europa.eu/resource/authority/language/FRA"
      },
      "attributes": {
        "title": {
          "xsd:string": "Consolidation: 172.216.321 - 1946-01-01"
        }
      }
    },
    {
      "uri": "https://fedlex.data.admin.ch/eli/cc/62/159_164_166/19460101/en",
      "type": "Expression",
      "references": {
        "language": "http://publications.europa.eu/resource/authority/language/ENG"
      },
      "attributes": {
        "title": {
          "xsd:string": "Consolidation: 172.216.321 - 1946-01-01"
        }
      }
    },
    {
      "uri": "http://publications.europa.eu/resource/authority/language/DEU",
      "type": [
        "Concept",
        "Language"
      ]
    },
    {
      "uri": "http://publications.europa.eu/resource/authority/language/ROH",
      "type": [
        "Concept",
        "Language"
      ]
    },
    {
      "uri": "http://publications.europa.eu/resource/authority/language/ITA",
      "type": [
        "Concept",
        "Language"
      ]
    },
    {
      "uri": "http://publications.europa.eu/resource/authority/language/FRA",
      "type": [
        "Concept",
        "Language"
      ]
    },
    {
      "uri": "http://publications.europa.eu/resource/authority/language/ENG",
      "type": [
        "Concept",
        "Language"
      ]
    }
  ],
  "graph": "https://fedlex.data.admin.ch/eli/cc/62/159_164_166/19460101/graph",
  "facets": {
    "consolidates": [
      {
        "dateDocument": "1946-01-15",
        "expression": {
          "http://publications.europa.eu/resource/authority/language/DEU": {
            "memorialLabel": "AS 62 159",
            "title": "Verfügung des eidgenössischen Volkswirtschaftsdepartements vom 15. Januar 1946 über die selbständige Erledigung von Geschäften durch den Vizedirektor, die Sektionen und das Direktionssekretariat des Bundesamtes für Industrie, Gewerbe und Arbeit "
          },
          "http://publications.europa.eu/resource/authority/language/FRA": {
            "memorialLabel": "RO 62 164",
            "title": "Ordonnance du département fédéral de l'économie publique du 15 janvier 1946 autorisant le sous-directeur, les sections et le secrétariat de la direction de l'office fédéral de l'industrie, des arts et métiers et du travail à régler de leur chef certaines affaires "
          },
          "http://publications.europa.eu/resource/authority/language/ITA": {
            "memorialLabel": "RU 62 166",
            "title": "Ordinanza del Dipartimento federale dell'economia pubblica del 15 gennaio 1946 che autorizza il vice direttore, le sezioni e il segretariato della direzione dell'Ufficio federale dell'industria, delle arti e mestieri e del lavoro a sbrigare da sè certi affari "
          }
        },
        "processType": "https://fedlex.data.admin.ch/vocabulary/type-procedure/ord",
        "uri": "https://fedlex.data.admin.ch/eli/oc/62/159_164_166"
      }
    ],
    "classifiedByTaxonomyEntryLabel_raw": "172.216.321",
    "consolidationAbstract": {
      "typeDocumentBroader": "https://fedlex.data.admin.ch/vocabulary/resource-type/47",
      "dateNoLongerInForce": "2003-02-01",
      "typeDocument": "https://fedlex.data.admin.ch/vocabulary/resource-type/26",
      "titles": {
        "http://publications.europa.eu/resource/authority/language/DEU": {
          "title": "Verfügung des eidgenössischen Volkswirtschaftsdepartements vom 15. Januar 1946 über die selbständige Erledigung von Geschäften durch den Vizedirektor, die Sektionen und das Direktionssekretariat des Bundesamtes für Industrie, Gewerbe und Arbeit "
        },
        "http://publications.europa.eu/resource/authority/language/FRA": {
          "title": "Ordonnance du département fédéral de l'économie publique du 15 janvier 1946 autorisant le sous-directeur, les sections et le secrétariat de la direction de l'office fédéral de l'industrie, des arts et métiers et du travail à régler de leur chef certaines affaires "
        },
        "http://publications.europa.eu/resource/authority/language/ITA": {
          "title": "Ordinanza del Dipartimento federale dell'economia pubblica del 15 gennaio 1946 che autorizza il vice direttore, le sezioni e il segretariato della direzione dell'Ufficio federale dell'industria, delle arti e mestieri e del lavoro a sbrigare da sè certi affari "
        }
      }
    },
    "classifiedByTaxonomyEntry": "https://fedlex.data.admin.ch/vocabulary/legal-taxonomy/5331",
    "classifiedByTaxonomyEntryLabel_sort": "00172.00216.00321",
    "theme": {
      "themeId": "1",
      "themeUri": "https://fedlex.data.admin.ch/vocabulary/legal-taxonomy/4713"
    },
    "impacts": [
      {
        "impactDate": "1946-01-01",
        "informationSource": "https://fedlex.data.admin.ch/vocabulary/information-source/data-from-geschaeftsstaende",
        "fromAct": "https://fedlex.data.admin.ch/eli/oc/62/159_164_166",
        "language": [
          "http://publications.europa.eu/resource/authority/language/DEU"
        ],
        "impactType": "https://fedlex.data.admin.ch/vocabulary/impact-type/5",
        "decisionDate": "1946-01-01",
        "historicalImpact": false
      },
      {
        "impactDate": "1946-01-01",
        "informationSource": "https://fedlex.data.admin.ch/vocabulary/information-source/data-from-geschaeftsstaende",
        "fromAct": "https://fedlex.data.admin.ch/eli/oc/62/159_164_166",
        "language": [
          "http://publications.europa.eu/resource/authority/language/FRA"
        ],
        "impactType": "https://fedlex.data.admin.ch/vocabulary/impact-type/5",
        "decisionDate": "1946-01-01",
        "historicalImpact": false
      },
      {
        "impactDate": "1946-01-01",
        "informationSource": "https://fedlex.data.admin.ch/vocabulary/information-source/data-from-geschaeftsstaende",
        "fromAct": "https://fedlex.data.admin.ch/eli/oc/62/159_164_166",
        "language": [
          "http://publications.europa.eu/resource/authority/language/ITA"
        ],
        "impactType": "https://fedlex.data.admin.ch/vocabulary/impact-type/5",
        "decisionDate": "1946-01-01",
        "historicalImpact": false
      }
    ],
    "classifiedByTaxonomyEntryLabel": {
      "de": "SR 172.216.321",
      "fr": "RS 172.216.321",
      "it": "RS 172.216.321"
    }
  },
  "timestampms": null
}
