{
  "data": {
    "uri": "https://fedlex.data.admin.ch/eli/cc/2000/295",
    "type": [
      "ConsolidationAbstract",
      "Work"
    ],
    "attributes": {
      "dateDocument": {
        "xsd:date": "1998-01-29"
      },
      "basicAct": {
        "rdfs:Resource": "https://fedlex.data.admin.ch/eli/oc/2000/295"
      },
      "typeDocument": {
        "rdfs:Resource": "https://fedlex.data.admin.ch/vocabulary/resource-type/31"
      },
      "dateEntryInForce": {
        "xsd:date": "1998-02-28"
      }
    },
    "references": {
      "classifiedByTaxonomyEntry": "https://fedlex.data.admin.ch/vocabulary/legal-taxonomy/238",
      "isRealizedBy": [
        "https://fedlex.data.admin.ch/eli/cc/2000/295/de",
        "https://fedlex.data.admin.ch/eli/cc/2000/295/fr",
        "https://fedlex.data.admin.ch/eli/cc/2000/295/it"
      ]
    }
  },
  "included": [
    {
      "uri": "https://fedlex.data.admin.ch/vocabulary/legal-taxonomy/238",
      "type": [
        "Concept",
        "LegalTaxonomy"
      ]
    },
    {
      "uri": "https://fedlex.data.admin.ch/eli/cc/2000/295/de",
      "type": "Expression",
      "references": {
        "language": "http://publications.europa.eu/resource/authority/language/DEU"
      },
      "attributes": {
        "title": {
          "xsd:string": "Vereinbarung <bd>vom 29. Januar 1998</bd> zwischen dem Schweizerischen Bundesrat und der Regierung der Republik Estland über die gegenseitige Aufhebung der Visumpflicht"
        }
      }
    },
    {
      "uri": "https://fedlex.data.admin.ch/eli/cc/2000/295/fr",
      "type": "Expression",
      "references": {
        "language": "http://publications.europa.eu/resource/authority/language/FRA"
      },
      "attributes": {
        "title": {
          "xsd:string": "Accord <bd>du 29 janvier 1998</bd> entre le Conseil fédéral suisse et  le Gouvernement de la République d'Estonie sur la suppression réciproque de l'obligation du visa"
        }
      }
    },
    {
      "uri": "https://fedlex.data.admin.ch/eli/cc/2000/295/it",
      "type": "Expression",
      "references": {
        "language": "http://publications.europa.eu/resource/authority/language/ITA"
      },
      "attributes": {
        "title": {
          "xsd:string": "Accordo <bd>del 29 gennaio 1998</bd> tra il Consiglio federale svizzero e il Governo della Repubblica d'Estonia concernente la soppressione reciproca dell'obbligo del visto"
        }
      }
    },
    {
      "uri": "http://publications.europa.eu/resource/authority/language/DEU",
      "type": [
        "Concept",
        "Language"
      ]
    },
    {
      "uri": "http://publications.europa.eu/resource/authority/language/FRA",
      "type": [
        "Concept",
        "Language"
      ]
    },
    {
      "uri": "http://publications.europa.eu/resource/authority/language/ITA",
      "type": [
        "Concept",
        "Language"
      ]
    }
  ],
  "graph": "https://fedlex.data.admin.ch/eli/cc/2000/295/graph",
  "facets": {
    "typeDocumentBroader": "https://fedlex.data.admin.ch/vocabulary/resource-type/49",
    "consolidates": [
      {
        "dateDocument": "1998-01-29",
        "expression": {
          "http://publications.europa.eu/resource/authority/language/DEU": {
            "manifestation": [
              {
                "format": "http://publications.europa.eu/resource/authority/file-type/DOC",
                "fileUrl": "https://fedlex.data.admin.ch/filestore/fedlex.data.admin.ch/eli/oc/2000/295/de/doc/fedlex-data-admin-ch-eli-oc-2000-295-de-doc.doc",
                "uri": "https://fedlex.data.admin.ch/eli/oc/2000/295/de/doc"
              },
              {
                "format": "http://publications.europa.eu/resource/authority/file-type/PDF",
                "fileUrl": "https://fedlex.data.admin.ch/filestore/fedlex.data.admin.ch/eli/oc/2000/295/de/pdf-a/fedlex-data-admin-ch-eli-oc-2000-295-de-pdf-a.pdf",
                "uri": "https://fedlex.data.admin.ch/eli/oc/2000/295/de/pdf-a"
              },
              {
                "format": "http://publications.europa.eu/resource/authority/file-type/PDFX",
                "fileUrl": "https://fedlex.data.admin.ch/filestore/fedlex.data.admin.ch/eli/oc/2000/295/de/pdf-x/fedlex-data-admin-ch-eli-oc-2000-295-de-pdf-x.pdf",
                "uri": "https://fedlex.data.admin.ch/eli/oc/2000/295/de/pdf-x"
              }
            ],
            "memorialLabel": "AS 2000 1921",
            "title": "Vereinbarung <bd> zwischen dem Schweizerischen Bundesrat und der Regierung der Republik Estland über die gegenseitige Aufhebung der Visumpflicht"
          },
          "http://publications.europa.eu/resource/authority/language/FRA": {
            "manifestation": [
              {
                "format": "http://publications.europa.eu/resource/authority/file-type/PDF",
                "fileUrl": "https://fedlex.data.admin.ch/filestore/fedlex.data.admin.ch/eli/oc/2000/295/fr/pdf-a/fedlex-data-admin-ch-eli-oc-2000-295-fr-pdf-a.pdf",
                "uri": "https://fedlex.data.admin.ch/eli/oc/2000/295/fr/pdf-a"
              },
              {
                "format": "http://publications.europa.eu/resource/authority/file-type/DOC",
                "fileUrl": "https://fedlex.data.admin.ch/filestore/fedlex.data.admin.ch/eli/oc/2000/295/fr/doc/fedlex-data-admin-ch-eli-oc-2000-295-fr-doc.doc",
                "uri": "https://fedlex.data.admin.ch/eli/oc/2000/295/fr/doc"
              },
              {
                "format": "http://publications.europa.eu/resource/authority/file-type/PDFX",
                "fileUrl": "https://fedlex.data.admin.ch/filestore/fedlex.data.admin.ch/eli/oc/2000/295/fr/pdf-x/fedlex-data-admin-ch-eli-oc-2000-295-fr-pdf-x.pdf",
                "uri": "https://fedlex.data.admin.ch/eli/oc/2000/295/fr/pdf-x"
              }
            ],
            "memorialLabel": "RO 2000 1921",
            "title": "Accord <bd> entre le Conseil fédéral suisse et  le Gouvernement de la République d'Estonie sur la suppression réciproque de l'obligation du visa"
          },
          "http://publications.europa.eu/resource/authority/language/ITA": {
            "manifestation": [
              {
                "format": "http://publications.europa.eu/resource/authority/file-type/PDF",
                "fileUrl": "https://fedlex.data.admin.ch/filestore/fedlex.data.admin.ch/eli/oc/2000/295/it/pdf-a/fedlex-data-admin-ch-eli-oc-2000-295-it-pdf-a.pdf",
                "uri": "https://fedlex.data.admin.ch/eli/oc/2000/295/it/pdf-a"
              },
              {
                "format": "http://publications.europa.eu/resource/authority/file-type/DOC",
                "fileUrl": "https://fedlex.data.admin.ch/filestore/fedlex.data.admin.ch/eli/oc/2000/295/it/doc/fedlex-data-admin-ch-eli-oc-2000-295-it-doc.doc",
                "uri": "https://fedlex.data.admin.ch/eli/oc/2000/295/it/doc"
              },
              {
                "format": "http://publications.europa.eu/resource/authority/file-type/PDFX",
                "fileUrl": "https://fedlex.data.admin.ch/filestore/fedlex.data.admin.ch/eli/oc/2000/295/it/pdf-x/fedlex-data-admin-ch-eli-oc-2000-295-it-pdf-x.pdf",
                "uri": "https://fedlex.data.admin.ch/eli/oc/2000/295/it/pdf-x"
              }
            ],
            "memorialLabel": "RU 2000 1921",
            "title": "Accordo <bd> tra il Consiglio federale svizzero e il Governo della Repubblica d'Estonia concernente la soppressione reciproca dell'obbligo del visto"
          }
        },
        "responsibilityOf": "https://fedlex.data.admin.ch/vocabulary/legal-institution/41",
        "processType": "https://fedlex.data.admin.ch/vocabulary/type-procedure/ord",
        "uri": "https://fedlex.data.admin.ch/eli/oc/2000/295"
      }
    ],
    "sortingDate": "1998-02-28",
    "theme": {
      "themeId": "0.1",
      "themeUri": "https://fedlex.data.admin.ch/vocabulary/legal-taxonomy/1"
    },
    "impacts": [
      {
        "impactDate": "1998-02-28",
        "informationSource": "https://fedlex.data.admin.ch/vocabulary/information-source/data-from-geschaeftsstaende",
        "fromAct": "https://fedlex.data.admin.ch/eli/oc/2000/295",
        "language": [
          "http://publications.europa.eu/resource/authority/language/ITA"
        ],
        "impactType": "https://fedlex.data.admin.ch/vocabulary/impact-type/5",
        "decisionDate": "1998-02-28",
        "historicalImpact": false
      },
      {
        "impactDate": "1998-02-28",
        "informationSource": "https://fedlex.data.admin.ch/vocabulary/information-source/data-from-geschaeftsstaende",
        "fromAct": "https://fedlex.data.admin.ch/eli/oc/2000/295",
        "language": [
          "http://publications.europa.eu/resource/authority/language/FRA"
        ],
        "impactType": "https://fedlex.data.admin.ch/vocabulary/impact-type/5",
        "decisionDate": "1998-02-28",
        "historicalImpact": false
      },
      {
        "impactDate": "1998-02-28",
        "informationSource": "https://fedlex.data.admin.ch/vocabulary/information-source/data-from-geschaeftsstaende",
        "fromAct": "https://fedlex.data.admin.ch/eli/oc/2000/295",
        "language": [
          "http://publications.europa.eu/resource/authority/language/DEU"
        ],
        "impactType": "https://fedlex.data.admin.ch/vocabulary/impact-type/5",
        "decisionDate": "1998-02-28",
        "historicalImpact": false
      }
    ],
    "title": {
      "de": "Vereinbarung <bd>vom 29. Januar 1998</bd> zwischen dem Schweizerischen Bundesrat und der Regierung der Republik Estland über die gegenseitige Aufhebung der Visumpflicht",
      "it": "Accordo <bd>del 29 gennaio 1998</bd> tra il Consiglio federale svizzero e il Governo della Repubblica d'Estonia concernente la soppressione reciproca dell'obbligo del visto",
      "fr": "Accord <bd>du 29 janvier 1998</bd> entre le Conseil fédéral suisse et  le Gouvernement de la République d'Estonie sur la suppression réciproque de l'obligation du visa"
    },
    "classifiedByTaxonomyEntryLabel": {
      "de": "SR 0.142.113.342",
      "fr": "RS 0.142.113.342",
      "it": "RS 0.142.113.342"
    },
    "archivingDate": "1998-02-28"
  },
  "timestampms": null
}
